{
    "id": 1,
    "loan_id": 1,
    "code": "PAY000001-2020",
    "procedure_modality_id": 48,
    "estimated_date": "2020-08-31",
    "quota_number": 1,
    "estimated_quota": "1065.74",
    "penal_payment": "0",
    "accumulated_payment": "0",
    "interest_payment": "369.86",
    "capital_payment": "695.88",
    "penal_remaining": "0",
    "accumulated_remaining": "0",
    "state_id": 5,
    "role_id": 91,
    "validated": false,
    "voucher": "5624",
    "paid_by": "T",
    "affiliate_id": 57950,
    "payment_type_id": 1,
    "description": "Por pago de mora",
    "created_at": "2020-08-05T14:05:54.000000Z",
    "updated_at": "2020-08-05T17:47:34.000000Z",
    "deleted_at": null,
    "state": {
        "id": 5,
        "name": "Pendiente de Pago",
        "description": "Registro de pago pendiente"
    }
}